./.gitignore
./PKG-INFO
./README.md
./cli.py
./config.yaml
./consolidator.py
./db_tracker.py
./dbmanager.sh
./deployment_checker.py
./documentation_updater.py
./pyproject.toml
./repository_scanner.py
./requirements.txt
db_archivist-0.0.4.dist-info/METADATA
db_archivist-0.0.4.dist-info/WHEEL
db_archivist-0.0.4.dist-info/entry_points.txt
db_archivist-0.0.4.dist-info/RECORD
