Metadata-Version: 2.4
Name: db-archivist
Version: 0.0.4
Summary: Database Script Manager CLI for managing scripts across multiple repositories with deployment tracking
Project-URL: Homepage, https://github.com/douglaschalegre/dbmanager
Project-URL: Repository, https://github.com/douglaschalegre/dbmanager.git
Project-URL: Issues, https://github.com/douglaschalegre/dbmanager/issues
Author-email: Douglas Chalegre <douglas.chalegre@gmail.com>
License: MIT
Keywords: cli,database,deployment,postgresql,scripts
Classifier: Development Status :: 4 - Beta
Classifier: Intended Audience :: Developers
Classifier: License :: OSI Approved :: MIT License
Classifier: Operating System :: OS Independent
Classifier: Programming Language :: Python :: 3
Classifier: Programming Language :: Python :: 3.8
Classifier: Programming Language :: Python :: 3.9
Classifier: Programming Language :: Python :: 3.10
Classifier: Programming Language :: Python :: 3.11
Classifier: Programming Language :: Python :: 3.12
Classifier: Topic :: Database
Classifier: Topic :: Software Development :: Build Tools
Classifier: Topic :: System :: Systems Administration
Requires-Python: >=3.8
Requires-Dist: click>=8.0.0
Requires-Dist: psycopg2-binary>=2.9.0
Requires-Dist: pyyaml>=6.0
Provides-Extra: dev
Requires-Dist: black>=23.0.0; extra == 'dev'
Requires-Dist: flake8>=6.0.0; extra == 'dev'
Requires-Dist: mypy>=1.0.0; extra == 'dev'
Requires-Dist: pytest>=7.0.0; extra == 'dev'
